setup.cfg
setup.py
postchi/__init__.py
postchi/backend.py
postchi/mails.py
postchi.egg-info/PKG-INFO
postchi.egg-info/SOURCES.txt
postchi.egg-info/dependency_links.txt
postchi.egg-info/requires.txt
postchi.egg-info/top_level.txt
tests/__init__.py
tests/tests.py