Metadata-Version: 1.1
Name: postchi
Version: 0.1.2
Summary: A reliable async email sender for django
Home-page: https://github.com/inb-co/postchi
Author: Mahdi Zareie
Author-email: mahdi.elf@gmail.com
License: UNKNOWN
Keywords: postchi,async email sender,django email backend
Platform: UNKNOWN
Classifier: Development Status :: 5 - Production/Stable
Classifier: Topic :: Utilities
Classifier: License :: OSI Approved :: BSD License
